{
  "favorites": [
    {
      "id": "5875",
      "track_id": "2191927",
      "name": "44. Manhattan Sunset",
      "duration": 197,
      "artist_name": "Michał Jałochowski",
      "album_name": "Smooth Jazz Club / Ballads",
      "releasedate": "2024-08-02",
      "album_image": "https://usercontent.jamendo.com?type=album&id=575950&width=300&trackid=2191927",
      "audio": "https://prod-1.storage.jamendo.com/?trackid=2191927&format=mp31&from=rKpy1TaBgROIbkt%2Fa46CQA%3D%3D%7CJ77hMiaqbYEBjedVXdVWWQ%3D%3D",
      "shareurl": "https://www.jamendo.com/track/2191927",
      "image": "https://usercontent.jamendo.com?type=album&id=575950&width=300&trackid=2191927"
    },
    {
      "id": "e707",
      "track_id": "2043033",
      "name": "The Last Handshake",
      "duration": 253,
      "artist_name": "Ogi Feel the Beat",
      "album_name": "Stronger than the Problems",
      "releasedate": "2023-07-12",
      "album_image": "https://usercontent.jamendo.com?type=album&id=526542&width=300&trackid=2043033",
      "audio": "https://prod-1.storage.jamendo.com/?trackid=2043033&format=mp31&from=8OAruHIRWhTmceACxh94NQ%3D%3D%7C5QBlNDUgQAQfGhusMTAmZA%3D%3D",
      "shareurl": "https://www.jamendo.com/track/2043033",
      "image": "https://usercontent.jamendo.com?type=album&id=526542&width=300&trackid=2043033"
    },
    {
      "id": "bec6",
      "track_id": "2198699",
      "name": "Dance With Me",
      "duration": 362,
      "artist_name": "LaChean",
      "album_name": "Intelligentia Iuncturam",
      "releasedate": "2024-09-01",
      "album_image": "https://usercontent.jamendo.com?type=album&id=578408&width=300&trackid=2198699",
      "audio": "https://prod-1.storage.jamendo.com/?trackid=2198699&format=mp31&from=vJC2oi1leXtoTbLEPha8tA%3D%3D%7CbYFRMtspy0f2%2BtK3RbPN0Q%3D%3D",
      "shareurl": "https://www.jamendo.com/track/2198699",
      "image": "https://usercontent.jamendo.com?type=album&id=578408&width=300&trackid=2198699"
    },
    {
      "id": "aab8",
      "track_id": "2225331",
      "name": "Tropical Pop Dance",
      "duration": 114,
      "artist_name": "Jackson Frost",
      "album_name": "Summer Dance Pop",
      "releasedate": "2024-12-23",
      "album_image": "https://usercontent.jamendo.com?type=album&id=590569&width=300&trackid=2225331",
      "audio": "https://prod-1.storage.jamendo.com/?trackid=2225331&format=mp31&from=Cdo8DQ1XpHABAInvciJE8Q%3D%3D%7Cuyf%2FhOyS%2F%2B2aVswU2PBf1A%3D%3D",
      "shareurl": "https://www.jamendo.com/track/2225331",
      "image": "https://usercontent.jamendo.com?type=album&id=590569&width=300&trackid=2225331"
    },
    {
      "id": "7ac5",
      "track_id": "246560",
      "name": "I Don't Wanna Be",
      "duration": 200,
      "artist_name": "Ades Vapor",
      "album_name": "Get High EP (Re-Edit)",
      "releasedate": "2008-11-28",
      "album_image": "https://usercontent.jamendo.com?type=album&id=35657&width=300&trackid=246560",
      "audio": "https://prod-1.storage.jamendo.com/?trackid=246560&format=mp31&from=EwhT1XKmgT1U0bMIXU6nfg%3D%3D%7CmX4fA7irfl1u7Umbsk134Q%3D%3D",
      "shareurl": "https://www.jamendo.com/track/246560",
      "image": "https://usercontent.jamendo.com?type=album&id=35657&width=300&trackid=246560"
    },
    {
      "id": "9d72",
      "track_id": "1593515",
      "name": "Alan Walker - Different World (Andrey Brailitsa Remix)",
      "duration": 199,
      "artist_name": "Andrey Brailitsa",
      "album_name": "Alan Walker - Different World (Andrey Brailitsa Remix)",
      "releasedate": "2018-11-19",
      "album_image": "https://usercontent.jamendo.com?type=album&id=296659&width=300&trackid=1593515",
      "audio": "https://prod-1.storage.jamendo.com/?trackid=1593515&format=mp31&from=R4U1ffgmbtFQuLUJdZUw8Q%3D%3D%7C5K5kePrPMmgW1kmivcz2wQ%3D%3D",
      "shareurl": "https://www.jamendo.com/track/1593515",
      "image": "https://usercontent.jamendo.com?type=album&id=296659&width=300&trackid=1593515"
    }
  ]
}